failextract/__init__.py
failextract/cli.py
failextract/configuration.py
failextract/failextract.py
failextract/py.typed
failextract/api/__init__.py
failextract/api/events/__init__.py
failextract/api/events/system.py
failextract/api/protocols/__init__.py
failextract/api/protocols/extraction.py
failextract/api/protocols/formatting.py
failextract/api/protocols/integration.py
failextract/api/registry/__init__.py
failextract/api/registry/components.py
failextract/core/__init__.py
failextract/core/registry.py
failextract/core/analysis/__init__.py
failextract/core/analysis/context_extractor.py
failextract/core/extraction/__init__.py
failextract/core/extraction/fixtures.py
failextract/core/formatters/__init__.py
failextract/core/formatters/base.py
failextract/core/formatters/csv.py
failextract/core/formatters/json.py
failextract/core/formatters/markdown.py
failextract/core/formatters/registry.py
failextract/core/formatters/xml.py
failextract/core/formatters/yaml.py
failextract/integrations/__init__.py
failextract/integrations/common/__init__.py
failextract/integrations/common/types.py
failextract-1.0.0.dist-info/METADATA
failextract-1.0.0.dist-info/WHEEL
failextract-1.0.0.dist-info/entry_points.txt
failextract-1.0.0.dist-info/licenses/LICENSE
failextract-1.0.0.dist-info/RECORD
