Metadata-Version: 2.4
Name: failextract
Version: 1.0.0
Summary: Comprehensive test failure extraction and reporting library for pytest
Project-URL: Homepage, https://github.com/dingo-actual/failextract
Project-URL: Repository, https://github.com/dingo-actual/failextract
Project-URL: Issues, https://github.com/dingo-actual/failextract/issues
Project-URL: Changelog, https://github.com/dingo-actual/failextract/blob/main/CHANGELOG.md
Author-email: Ryan Taylor <ryan@beta-reduce.net>
License: Apache-2.0
License-File: LICENSE
Keywords: analysis,debugging,pytest,reporting,test-failures,testing
Classifier: Development Status :: 5 - Production/Stable
Classifier: Framework :: Pytest
Classifier: Intended Audience :: Developers
Classifier: Operating System :: OS Independent
Classifier: Programming Language :: Python :: 3
Classifier: Programming Language :: Python :: 3.11
Classifier: Programming Language :: Python :: 3.12
Classifier: Programming Language :: Python :: 3.13
Classifier: Topic :: Software Development :: Quality Assurance
Classifier: Topic :: Software Development :: Testing
Classifier: Typing :: Typed
Requires-Python: >=3.11
Provides-Extra: all
Requires-Dist: pydantic>=1.10; extra == 'all'
Requires-Dist: pyyaml>=5.4; extra == 'all'
Requires-Dist: rich>=12.0; extra == 'all'
Requires-Dist: typer>=0.7; extra == 'all'
Provides-Extra: cli
Requires-Dist: rich>=12.0; extra == 'cli'
Requires-Dist: typer>=0.7; extra == 'cli'
Provides-Extra: config
Requires-Dist: pydantic>=1.10; extra == 'config'
Provides-Extra: development
Requires-Dist: hypothesis>=6.50; extra == 'development'
Requires-Dist: mypy>=1.0; extra == 'development'
Requires-Dist: pytest-cov>=4.0; extra == 'development'
Requires-Dist: pytest>=7.0; extra == 'development'
Requires-Dist: ruff>=0.1.0; extra == 'development'
Provides-Extra: docs
Requires-Dist: myst-parser>=1.0; extra == 'docs'
Requires-Dist: sphinx-autobuild>=2021.1; extra == 'docs'
Requires-Dist: sphinx-autodoc-typehints>=1.20; extra == 'docs'
Requires-Dist: sphinx-rtd-theme>=1.0; extra == 'docs'
Requires-Dist: sphinx>=5.0; extra == 'docs'
Provides-Extra: formatters
Requires-Dist: pyyaml>=5.4; extra == 'formatters'
